{
    "model": {
        "num_layers_encoder": 7,
        "num_layers_decoder": 7,
        "d_model": 256,
        "dff": 512,
        "num_heads": 4
    },
    "trainings": {
        "production": {
            "repetitions": 0,
            "time": 0,
            "loss_history": [
                "0"
            ],
            "acc_history": [
                "0"
            ]
        },
        "comedy": {
            "repetitions": 150,
            "time": 9812,
            "loss_history": [
                "7.0323",
                "4.8886",
                "3.9470",
                "3.6819",
                "3.5358",
                "3.3877",
                "3.2354",
                "3.1090",
                "2.9456",
                "2.8294",
                "2.7280",
                "2.6144",
                "2.6504",
                "2.4477",
                "2.3676",
                "2.2557",
                "2.1711",
                "2.0897",
                "2.0022",
                "1.9444",
                "1.8591",
                "1.7771",
                "1.7064",
                "1.6363",
                "1.5717",
                "1.5096",
                "1.4521",
                "1.3935",
                "1.3329",
                "1.2805",
                "1.2288",
                "1.1810",
                "1.1316",
                "1.0876",
                "1.0436",
                "1.0031",
                "0.9644",
                "0.9274",
                "0.8885",
                "0.8555",
                "0.8219",
                "0.7911",
                "0.7611",
                "0.7324",
                "0.7073",
                "0.6811",
                "0.6559",
                "0.6356",
                "0.6141",
                "0.5927",
                "0.5712",
                "0.5538",
                "0.5371",
                "0.5211",
                "0.5102",
                "0.4907",
                "0.4784",
                "0.4633",
                "0.4495",
                "0.4379",
                "0.4265",
                "0.4145",
                "0.4032",
                "0.3939",
                "0.3841",
                "0.3749",
                "0.3682",
                "0.3606",
                "0.3510",
                "0.3451",
                "0.3368",
                "0.3275",
                "0.3231",
                "0.3169",
                "0.3103",
                "0.3038",
                "0.2990",
                "0.2915",
                "0.2886",
                "0.2823",
                "0.2760",
                "0.2719",
                "0.2670",
                "0.2627",
                "0.2599",
                "0.2557",
                "0.2511",
                "0.2465",
                "0.2434",
                "0.2394",
                "0.2353",
                "0.2317",
                "0.2289",
                "0.2262",
                "0.2237",
                "0.2206",
                "0.2169",
                "0.2153",
                "0.2106",
                "0.2079",
                "0.2069",
                "0.2032",
                "0.2006",
                "0.1975",
                "0.1961",
                "0.1944",
                "0.1920",
                "0.1899",
                "0.1867",
                "0.1850",
                "0.1829",
                "0.1815",
                "0.1799",
                "0.1761",
                "0.1750",
                "0.1725",
                "0.1707",
                "0.1693",
                "0.1681",
                "0.1658",
                "0.1641",
                "0.1610",
                "0.1610",
                "0.1585",
                "0.1559",
                "0.1562",
                "0.1545",
                "0.1525",
                "0.1530",
                "0.1501",
                "0.1488",
                "0.1473",
                "0.1463",
                "0.1441",
                "0.1432",
                "0.1416",
                "0.1397",
                "0.1396",
                "0.1379",
                "0.1368",
                "0.1351",
                "0.1333",
                "0.1334",
                "0.1318",
                "0.1315",
                "0.1302",
                "0.1291",
                "0.1285",
                "0.1278",
                "0.1259",
                "0.1287"
            ],
            "acc_history": [
                "0.1760",
                "0.2189",
                "0.2857",
                "0.3105",
                "0.3238",
                "0.3353",
                "0.3463",
                "0.3549",
                "0.3670",
                "0.3739",
                "0.3804",
                "0.3877",
                "0.3803",
                "0.3994",
                "0.4054",
                "0.4161",
                "0.4246",
                "0.4329",
                "0.4423",
                "0.4473",
                "0.4578",
                "0.4672",
                "0.4762",
                "0.4847",
                "0.4927",
                "0.5007",
                "0.5077",
                "0.5156",
                "0.5245",
                "0.5323",
                "0.5392",
                "0.5461",
                "0.5531",
                "0.5605",
                "0.5666",
                "0.5731",
                "0.5789",
                "0.5848",
                "0.5918",
                "0.5970",
                "0.6027",
                "0.6079",
                "0.6132",
                "0.6179",
                "0.6224",
                "0.6273",
                "0.6319",
                "0.6355",
                "0.6400",
                "0.6434",
                "0.6477",
                "0.6518",
                "0.6540",
                "0.6574",
                "0.6598",
                "0.6639",
                "0.6661",
                "0.6694",
                "0.6723",
                "0.6744",
                "0.6771",
                "0.6796",
                "0.6815",
                "0.6840",
                "0.6858",
                "0.6881",
                "0.6897",
                "0.6910",
                "0.6936",
                "0.6937",
                "0.6963",
                "0.6982",
                "0.6992",
                "0.6999",
                "0.7021",
                "0.7034",
                "0.7043",
                "0.7061",
                "0.7069",
                "0.7080",
                "0.7099",
                "0.7102",
                "0.7113",
                "0.7124",
                "0.7131",
                "0.7137",
                "0.7154",
                "0.7158",
                "0.7164",
                "0.7178",
                "0.7183",
                "0.7195",
                "0.7198",
                "0.7203",
                "0.7215",
                "0.7220",
                "0.7226",
                "0.7228",
                "0.7242",
                "0.7248",
                "0.7254",
                "0.7253",
                "0.7266",
                "0.7269",
                "0.7276",
                "0.7278",
                "0.7283",
                "0.7282",
                "0.7299",
                "0.7296",
                "0.7307",
                "0.7306",
                "0.7304",
                "0.7321",
                "0.7321",
                "0.7329",
                "0.7329",
                "0.7337",
                "0.7334",
                "0.7346",
                "0.7348",
                "0.7347",
                "0.7355",
                "0.7356",
                "0.7369",
                "0.7361",
                "0.7368",
                "0.7373",
                "0.7372",
                "0.7382",
                "0.7375",
                "0.7383",
                "0.7390",
                "0.7392",
                "0.7391",
                "0.7396",
                "0.7407",
                "0.7397",
                "0.7405",
                "0.7405",
                "0.7411",
                "0.7417",
                "0.7411",
                "0.7419",
                "0.7420",
                "0.7419",
                "0.7426",
                "0.7425",
                "0.7430",
                "0.7430",
                "0.7429"
            ]
        }
    },
    "generations": {
        "temp_0.5": "\n\u00e0hi qu\u00e0nto a dir qual \u00e8ra \u00e8 c\u00f2sa d\u00f9ra\nn\u00f2va scender gi\u00f9 n\u00e9l v\u00ecso mi raccesi\nquella ch\u00e9 pi\u00f9 pareva pr\u00ecma ch\u00e9 'l m\u00f3ndo\n\npi\u00f9 \u00e8 s\u00f9, e volgi, e pi\u00f9 li\u00e8ve\nacci\u00f2 ch\u00e9 la m\u00eca virt\u00f9 men ti dice,\nver\u00e0ce amor ch\u00e9 'l piacer di d\u00eco dole.\n\nn\u00f3n \u00e8 s\u00e0nza cagion di ch\u00e9 tu m'accenti\nde la m\u00eca compagn\u00eca cost\u00f9i sovvenni,\n\u00e8 la cagion ch\u00e9 di t\u00f9tti li \u00e0ltri scandi\n\nlo t\u00e8mpo ch\u00e9 t\u00f9tto il r\u00e9gno \u00e8 f\u00e0tto fr\u00f9tto\nrispuose: vedi ch\u00e9 qu\u00e9sto \u00e8 tacer mio;\nma per ch\u00e9 d\u00eco s\u00f3gno ha pi\u00f9 a mena\n\nio v\u00e9ggio b\u00e8n c\u00f3me gi\u00e0 col\u00f9i ch\u00e9 brama\nne la mis\u00e8ria d\u00e9l cielo, ond'io rispuosi,\ne queste parole, a ch\u00e9 render vada.\n\nma per dar l\u00f9i esperi\u00e8nza piena,\na pi\u00e8 d\u00e9l v\u00e9ro il dubbio; ed \u00e8 nat\u00f9ra\nch'al tr\u00f2ppo di r\u00e8tro t\u00f9tto il ciel ten vede.\n\ns\u00ec ch\u00e9 'l pr\u00e9gno \u00e0ere in \u00e0cqua si con\nla m\u00e9nte m\u00eca da l'altra qual tu paqu\u00ecnci\ne 'l ciel vedrai inn\u00e0nzi ch\u00e9 si par\u00e8a\n\nveder lo s\u00f2l ch\u00e9 nostra v\u00ecsta ritorna:\nvedrai ben, s\u00f3vra quella g\u00e8nte vana.\ncos\u00ec s\u00e9n giva; e n\u00f3n cr\u00e8do ch\u00e9 sia,\n\nrispuose, c\u00f3me n\u00f3i restammo, ei\nl'antico d\u00e9l cammin se' in quella tratta\nch\u00e9 'nvidia giust\u00eczia vuole e piena.\n\nor ti parr\u00e0, se tu qu\u00ecnci argomenti,\nl'alto valor d\u00e9l voto, s'\u00e8 s\u00ec f\u00e0tto\nch\u00e9 la m\u00eca pervend\u00e9tta n\u00f3n ha riciso.\n\ne perche' m\u00e9no ammiri la parola,\ngu\u00e0rda il calor d\u00e9l s\u00f3le ch\u00e9 si fa vino,\ngi\u00f9nto a l'omor ch\u00e9 de la v\u00ecte cola.\n\ns\u00ec che, per salir n\u00f3n pu\u00f2 da la s\u00e9\nde la m\u00eca virt\u00f9 creat\u00f9ra sospesa,\nn\u00f3n ch\u00e9 la v\u00f3ce m\u00eca \u00e8 d\u00e9l mar n\u00f3n ha.\n\nper\u00f2 ch\u00e9 'l ben, ch'\u00e8 d\u00e9l t\u00f9o ch\u00e9\nn\u00f3n per se' s\u00ec ch\u00e9 parlar differenterebbe,\nspene, diss'io, \u00e8 a gu\u00ecsa ch\u00e9 vada al mai\n\nper\u00f2 ch\u00e9 andasse ver' lo s\u00f9o dil\u00e8tto\nde la m\u00eca gl\u00f2ria e d\u00e9l ciel mi la m\u00e9nte\ndi ch\u00e9 la m\u00e9nte m\u00eca \u00e8 t\u00e0nta pace.\n\ne qu\u00e9l ch\u00e9 pi\u00f9 vede la perse a' compriega\nd\u00e9l v\u00ecso m\u00eco ne l'aspetto be\u00e0to f\u00ecglio\ndi qu\u00e9l ciel da se' mar pra s\u00f9 parte.\n\nse la ragion di l\u00f9i vede di martiri\nvede la c\u00f2sa in se' d\u00e9l gr\u00e0nde cortes\u00eca\nch\u00e9 n\u00e9l s\u00f9o m\u00e8zzo fece il l\u00f9me centro.\n\nqueste parole fu\u00f2r d\u00e9l d\u00f9ca mio;\ns\u00ec ch\u00e9 n\u00f2tte ne' sonno a voi n\u00f3n fura,\npensa la succession; pensa ch'al peggio.\n\no d\u00f3lce padre, d\u00ec, qu\u00e0le offensi\u00f3ne\nsi p\u00f9rga qui n\u00e9l g\u00ecro d\u00f3ve seconda,\ne 'l ventre inn\u00e0nzi a li \u00f2cchi s\u00ec t'assiero.\n\nall\u00f3ra il m\u00eco segnor, qu\u00e0si ammirando,\nmenane, disse, d\u00f9nque l\u00e0 've dici\nch'a l'universo de le saetti sue.\n\nma tu chi se', ch\u00e9 se' n\u00f3n ti p\u00e0rte\ndal t\u00e8mpo m\u00eco segnor, ch\u00e9 fu\u00f2r di s\u00f3tto\nio porsi 'l tra loro; e pi\u00f9 n\u00f3n sanno\n\na p\u00e9na d\u00f9nque di t\u00f9tti quanti giri,\nch\u00e9 'l s\u00f9o contr\u00e0rio m\u00f3ndo n\u00f3n s'impiglia,\nma pi\u00f9 \u00e8 dar di dubbiar pi\u00f9 pregno;\n\ne qu\u00e9lli a me: t\u00f9tti sar\u00e0n di a' mo\ns\u00f2n le sustanze ch\u00e9 t'appaion tondi,\ns\u00ec ch\u00e9 la v\u00ecta m\u00eca \u00e8 t\u00e0nto costa.\n\ne c\u00f3me 'l volger d\u00e9l ciel de la l\u00f9na\ncuopre e discuopre i liti s\u00e0nza posa,\ncos\u00ec \u00e8 forl\u00ec la m\u00eca v\u00ecta futura.\n\nn\u00f3n s\u00f2n rimase acerbe ne' mature f\u00e0re\nle membra mie di l\u00e0, ma s\u00f2n qui m\u00e9co\nc\u00f2l s\u00e0ngue s\u00f9o e c\u00f3n le s\u00f9e giunture.\n\nancor mi pu\u00f2 di l\u00e0 p\u00f2i ch\u00e9 si sazia\nin qu\u00e9sta vita, inf\u00ecno a qu\u00e9sta vita,\nn\u00f3n \u00e8 se n\u00f3n ch\u00e9 la divina lieta.\n\nvedi ch\u00e9 la g\u00e8nte ch\u00e9 l\u00ec \u00e8 queta,\nper ch\u00e9 'l maestro fa, in n\u00f2stro r\u00f9a\nc\u00f3n l'altrui, ch\u00e9 di ci\u00f2 n\u00f3n si diparte.\n\noh qu\u00e0nto 'l veder gelam\u00e9nte se l'arca\nd\u00e9l commendan ch'a la s.u.a. parv\u00e8nza\nper ch\u00e9 la m\u00eca m\u00e9nte pr\u00ecma fu s\u00ec v\u00ec\n\nn\u00e9l t\u00e8mpo ch\u00e9 'l f\u00f2co sec\u00f3ndo riede,\ngi\u00e0 m\u00e0i a bu\u00f2n voler, torn\u00f2 a l'ossa;\ne ci\u00f2 di v\u00ecva sp\u00e8ne fu mercede:\n\ndi v\u00ecva spene, ch\u00e9 mise la p\u00f2ssa\nne' prieghi fatti a d\u00eco per suscitarla,\ns\u00ec ch\u00e9 'l v\u00ecso t\u00f9o parlar n\u00f3n sazia.\n\nn\u00f3n so se tu se' ne' m\u00eco ti m\u00f2do\ndi ci\u00f2 ch\u00e9 'l ciel ch\u00e9 parlar mi risponde\na far ci\u00f2 ch\u00e9 n\u00f3n m\u00f2ria n\u00f3n \u00e8 sospesa\n\na quella f\u00f3ce ch\u00e9 queta \u00e8 queta,\ns\u00ec ch\u00e9 'l t\u00f9o cor, n\u00f9lla \u00e8 t\u00e0nto\nch\u00e9 n\u00f3n parlar m'inganna, se pi\u00f9 tarde.\n\ns\u00ec mi disse, e \u00ecndi si risp\u00f3sta\n\u00e8 tal, ch\u00e9 n\u00f3n per col\u00f9i ch\u00e9 n\u00f3n vo\na la dimanda, ch\u00e9 tal vede \u00e8 questa\n\nne' per \u00e0ltro argom\u00e9nto ch\u00e9 n\u00f3n paia.\n\n\ngi\u00e0 \u00e8ra in gi\u00f9sto \u00e0nco la pi\u00f9 bella,\nper ch\u00e9 'l m\u00f3ndo s\u00f9o p\u00f2co si ricorda\nd\u00e9l mar iosu\u00e8, com'el si chiamava; e 'l\n",
        "temp_0.6": "\n\u00e0hi qu\u00e0nto a dir qual \u00e8ra \u00e8 c\u00f2sa d\u00f9ra\nn\u00f2va torta, e li \u00e0ltri n\u00f3n si conce\nch\u00e9 'l t\u00f9o parlar m'infonde, se nostra.\n\ns'io n\u00f3n fossi dir de l'anime tristato;\ne qui \u00e8 bu\u00f2no c\u00f3n l'ali e c\u00f3i remi,\nquant\u00f9nque pu\u00f2, ciascun pinger s.u.a. \n\nn\u00f3n \u00e8ra ancor s\u00f9o cader commino scarto,\nma n\u00f3n so se tu sai, ch\u00e9 i suoi \na ch\u00e9 la m\u00eca m\u00e9nte tu n\u00f3n ti mandi\n\ncos\u00ec vedrai veggion di t\u00f9tti costoro.\n\n\nqu\u00e0ndo leggi, frate, a me rem\u00f2to\ndi m\u00f2rte intrato d\u00e9ntro a la tua rete\nio li sovvenni, e i lor dritti costumi.\n\nfer dispregi\u00e0re a me tutte altre sette,\ne 'l m\u00eco dir li par\u00e8a lor conviensie\nch\u00e9 s\u00f3tto i piedi un l\u00e0go ch\u00e9 per g\u00e8lo \u00e8.\n\no d\u00f3lce padre, d\u00ec, qu\u00e0le offensi\u00f3ne\nsi p\u00f9rga qui n\u00e9l g\u00ecro d\u00f3ve semo?.\ned elli a me: qui s\u00f2n li eresiarche\n\nc\u00f3n lor seguaci, d'ogne setta, e m\u00f3lto\npi\u00f9 n\u00f3n credi tu ch'a l'occhio n\u00f3n s'aspetta.\ne 'l d\u00f9ca m\u00eco di ch\u00e9 pianger discende\n\nparieno a la riva 'ntorno si grida;\nche' qui \u00e8 bu\u00f2no c\u00f3n l'ali e c\u00f3i remi,\nquant\u00f9nque pu\u00f2, ciascun pinger s.u.a. \n\nlo d\u00f9ca m\u00eco di s\u00f9bito mi prese,\nc\u00f3me 'l s\u00f9o vuol ch\u00e9 'n se' risponda,\ne quella n\u00f3n rispuose, ch\u00e9 l\u00f9ce \u00e8 me\n\nch\u00e9 dal s\u00f9o \u00e0estro mi fa contento;\nper che, se la st\u00e9lla si ti pi\u00f9 mena\ndi ch\u00e9 si vede, qual gi\u00f9 n\u00f3n si conce\n\ndal qual se 'l m\u00f3ndo la vostra sortesa\nsi riconosce, sona, e s\u00ec da lui,\nqual ti far\u00e0, per la m\u00e9nte di si te\n\nlungam\u00e9nte a qu\u00e9sta prima, se fame.\nl'antico \u00e8 qui t\u00e0rdo si risposta,\nne' quai mir\u00e0ndo m\u00eco dis\u00eco ha posa;\n\nma dimmi, se tu sai, dov'\u00e8 piccarda\nch\u00e9 tu n\u00f3n ti veder\u00f2 da bu\u00f2n s'i' l'appoggio\nla b\u00e8lla d\u00f2nna ch'a d\u00eco mi sazia tanta\n\n\u00e0mbo vegnon d\u00e9l gr\u00e8mbo di maria, e ago\ndisse sordello, a gu\u00e0rdia de la valle,\nper ch\u00e9 'l maestro acc\u00f2rto lo sospinse.\n\ndi qua, di l\u00e0, di gi\u00f9, diceva\nne l'altre prima; e p\u00f2i se tu riguardi\nch'io n\u00f3n lo 'ntender m\u00f2sso le parole.\n\nla m\u00eca donna, ch\u00e9 mi fu\u00f2r di ciglia\ndi qua, di l\u00e0, di gi\u00f9, disidetti;\nper ch'io 'ndugiai al f\u00ecne i bu\u00f2n sospiri,\n\nse orazi\u00f3ne in pr\u00ecma n\u00f3n m'aita\nch\u00e9 surga s\u00f9 di cuor ch\u00e9 in gr\u00e0zia viva\nla m\u00eca f\u00e0ma n\u00f3n guarda, e t\u00e0nto lutto\n\nl'anima m\u00eca cite, ch\u00e9 s\u00f2n contenta;\ne 'l m\u00e8zzo di c\u00f9i siede ogne pres\u00e8nte\ndi ch\u00e9 per parlar sarem n\u00f3n ti nostra.\n\nvedi c\u00f3me l'ha dritte v\u00e8rso 'l cielo,\na la m\u00eca d\u00f2nna dirizz\u00f2 lo spiro,\nch\u00e9 si condusse a tremar per ogne martiri.\n\nqu\u00e9sti ch\u00e9 m'\u00e8 a d\u00e8stra pi\u00f9 vicino,\nfr\u00e0te \u00e8 la cagion ch\u00e9 n\u00f3n veggion tota,\nmi fa sovvenir d\u00e9l m\u00f3ndo antico.\n\ni' fui col\u00f9i ch\u00e9 la ghisolabella\ncondussi a far la v\u00f2glia d\u00e9l marchese,\nc\u00f3me ch\u00e9 suoni la sconcia novella.\n\ne n\u00f3n pur io qui piango bolognese;\n\u00e0nzi n'\u00e8 qu\u00e9sto lu\u00f2go t\u00e0nto pieno,\nch\u00e9 n\u00f3n credetti volesse per diremo.\n\nvedi c\u00f3me l'ha dritte v\u00e8rso 'l cielo,\ntrattando l'aere c\u00f3n l'etterno penne,\nch\u00e9 n\u00f3n si mutan c\u00f3me mortal pelo.\n\ne qui per f\u00f2rza mi fu per malizia,\nma per trattar d\u00e9l b\u00e8n ch'i' vi trovai,\ndir\u00f2 e 'l v\u00e9ro a me n\u00f3n perder viva.\n\ntal mi fec'io, quai s\u00f2n color ch\u00e9 stanno,\nper altra via, ch\u00e9 fu s\u00ec \u00e0spra e forte,\nch\u00e9 lo salir s\u00f9; e s'altri n\u00f3n volesse\n\nlo ciel ch\u00e9 'ntese t\u00f9o \u00e0lto s'insaet\ntu 'l sai, ch\u00e9 di ch\u00e9 'n alc\u00f9n s'ingra\nla verit\u00e0 d\u00e9l cielo, a la m\u00e9nte qu\u00ec.\n\ncos\u00ec da qu\u00e9sta c\u00f3rte si diparte\nper la camp\u00e0gna d\u00e9l ciel ten vien viso,\ne fa di se' le sustanze cose fanno.\n\ns\u00ec si de la v\u00ecsta divina sempiterna\no s\u00e0nto 'l ciel ch'a se' in su la m\u00eca\nsinistra, ch'\u00e8 or da se' in se' riga.\n\ncos\u00ec beatr\u00ecce quella ch\u00e9 s\u00ec scorta;\ne se la m\u00e9nte tua b\u00e8n se' riguarda,\ntu n\u00f3n ti vedi dubbiar pi\u00f9 le foglie;\n\ne 'l d\u00f9ca m\u00eco di ch\u00e9 si discerne\nper la virt\u00f9 ch\u00e9 'l ciel vede \u00f3mbra fonde\na la fonda ch\u00e9 \u00e8 color confessare.\n\ncos\u00ec vede qu\u00e0nto pi\u00f9 gi\u00f9 si m\u00f3nde\nl'essere s\u00f9o ch\u00e9 la s.u.a. circunfe\nsarebbe al t\u00f9o l\u00f9me fu compiute.\n\nma l'alta virt\u00f9 ch\u00e9 l'ess\u00e8mpre si sp\u00ecra\nla l\u00f9ce d\u00e9l suggel parrebbe tutte;\nma la nat\u00f9ra d\u00e9l s\u00f9o \u00e8 f\u00e0tto vano\n\ne s\u00ec c\u00f3me qu\u00e0ndo i suoi maggi molti,\nle membra mie parole ch\u00e9 l\u00e0 gi\u00f9 vinse,\nqu\u00e0ndo la c\u00f3lpa pent\u00f9ta \u00e8 rimossa.\n",
        "temp_0.7": "\n\u00e0hi qu\u00e0nto a dir qual \u00e8ra \u00e8 c\u00f2sa d\u00f9ra\nn\u00f2va scender gi\u00f9 n\u00e9l v\u00ecso mi coperchia!\ned elli a me: qui n\u00f3n ha l\u00f2co sospetto\n\nn\u00f2stro segn\u00f3re in pr\u00ecma da san pi\u00e8tro\nch'ei ponesse le chiavi in s.u.a. balia\nc\u00e8rto n\u00f3n si volse se' di te aver fretta.\n\nlo d\u00f9ca m\u00eco dis\u00eco di qu\u00e9sto gl\u00f2bo\nfar disp\u00f3sto a col\u00f9i ch\u00e9 la s.u.a. \nc\u00e8rto n\u00f3n lagrimar se n\u00f3n lo 'ngegno;\n\nche' la b\u00e8lla d\u00f2nna ch\u00e9 mi chiam\u00f2 scarse\na d\u00eco sodisf\u00e0tto a s.u.a. follia,\nrispuose: qu\u00e0nto f\u00eca ch'io ti dicata?.\n\nond'elli a me: se 'l cons\u00ecglio sarebbe n\u00f2ta\ndi compagn\u00eca ad ogne mover d'anca,\nper ch'io al d\u00f9ca mio, fa ch\u00e9 tu trovi.\n\nall\u00f3r virgilio disse: dilli tosto:\n\"non s\u00f2n colui, n\u00f3n s\u00f2n col\u00f9i ch\u00e9 credi\nper altrim\u00e9nti fan di se' parole.\n\nn\u00f3n altrim\u00e9nti tu fan di n\u00f2stro l\u00e0gio\nper le quali, accian d\u00e9l bolognese?\",\nn\u00f3n per d\u00f9ro mio, ma per ch\u00e9 di s\u00f3tto\n\nlo d\u00f9ca m\u00eco di s\u00f9bito mi prese,\nc\u00f3me la m\u00e0dre ch'al rom\u00f3re \u00e8 desto.\ne 'l segnor mio, s\u00ec t\u00f2sto ch'i' odo,\n\ncos\u00ec a se' e l'ora cos\u00ec ne cose\ndi m\u00f2rte inpoco, e vederai la f\u00e0ccia\nper la tua dimanda tua \u00e8 tr\u00f2ppo ragio.\n\ne qu\u00e9lli a me: t\u00f9tti sar\u00e0n serrati\nqu\u00e0ndo di iosafat qui torneranno\nc\u00f3i corpi ch\u00e9 l\u00e0 s\u00f9 hanno lasciati.\n\ns\u00f9o cimit\u00e8ro da qu\u00e9sta p\u00e0rte hanno\nc\u00f3n la test'alta e c\u00f3n rabbiosa fame,\ns\u00ec ch\u00e9 par\u00e8a n\u00f3n chiede lor vegno.\n\ncos\u00ec tornavan la m\u00e0dre al s\u00f2l figliuolo;\ne l'altro di\u00e8tro a la v\u00ecsta c\u00f3n no\u00e8 puote,\nchi di\u00e8tro a se' le qua s\u00f9 n\u00f3n vede noi.\n\ncos\u00ec disse il maestro; e 'l s\u00e8nso trascorse\nper la v\u00eca de la l\u00f9nga e 'l cammino,\ne disse: or se' tu qui s\u00f9 dimando.\n\ncos\u00ec s\u00e9n v\u00e0nno su per l'onda bruna,\ne av\u00e0nti ch\u00e9 sien di l\u00e0 discese, ascolta\nda lor med\u00e9re a se' n\u00f3n fu gi\u00e0 deci.\n\nn\u00f3n avea pur nat\u00f9ra \u00ecvi la riva\ndi t\u00f9tto 'l b\u00e0lzo v\u00eca l\u00e0 gi\u00f9 di s\u00f3tto\ndrittam\u00e9nte n\u00e9l f\u00f3ndo de la s.u.a.\n\nlo v\u00ecso m\u00eco conforto, e io restammo,\nn\u00e9l s\u00f9o m\u00e8zzo 'l p\u00e8tto pr\u00ecma mi volge\nper la verit\u00e0 ch\u00e9 l\u00e0 gi\u00f9 n\u00f3n si consta\n\ndi lei, di sopra, in qu\u00e9sta vita,\nne la f\u00e0ccia s.u.a. qui gi\u00f9 dim\u00f2ra\nvirt\u00f9 al ciel sarebbe a chi tua notrina.\n\nla m\u00eca sete, ch\u00e9 mi rivolge lieta\nl'anima m\u00eca d\u00e9l torm\u00e9nto di s\u00f9o fatto\nch\u00e9 n\u00f3n si lascia v\u00ecncere a disio;\n\ne in t\u00e8rra lasciai la m\u00eca mem\u00f2ria\ns\u00ec ch\u00e9 'l m\u00eco s\u00e9gno n\u00f3n parlar diffuso\nin ch\u00e9 n\u00f3n potea perder molte alte spoglie.\n\ne c\u00f3me 'l volger d\u00e9l ciel cu' io venne\nli p\u00e0ssi miei per s\u00ec selvaggia strada,\ndanne un de' tuoi, a c\u00f9i n\u00f3i siamo a provo,\n\ne ch\u00e9 ne mostri l\u00e0 d\u00f3ve si gu\u00e0da\ne ch\u00e9 porti cost\u00f9i in su la groppa,\nche' n\u00f3n \u00e8 sp\u00ecrto ch\u00e9 per l'aere vada.\n\nchi \u00e8 cost\u00f9i ch\u00e9 di s\u00e0nza f\u00ecda m\u00f2rte\nch\u00e9 'l qu\u00e0le il fantolin de la g\u00e8nte strada\nper ch\u00e9 dovessi lor passeggi\u00e0re anzi?.\n\ndopo la tratta d'un sosp\u00ecro amaro,\ns\u00ec ch\u00e9 la f\u00e0ccia m\u00eca b\u00e8n far n\u00f3n basti\ns\u00f3tto 'l gov\u00e8rno d'un s\u00f2l galeotoni.\n\ncos\u00ec per li gr\u00e0n savi si confessa\nch\u00e9 la fen\u00ecce m\u00eca \u00e8 t\u00e0nto digiuna,\nch\u00e9 li \u00f2cchi suoi argovan vapori ;\n\ne venne a l'emisperio nostra giust\u00eczia\ndi t\u00e0nto grazia, ch\u00e9 l'amor d\u00e9l libra;\nvincer d\u00e9l t\u00e8mpo ch'elli \u00e8 di qua negna.\n\nc\u00f3me 'l m\u00e8zzo d\u00e9l ciel siede vento,\ns\u00e0nza gu\u00e8rra ne' cuor de' suoi tiranni;\nma tr\u00e9 per di l\u00e0 \u00f3nde venner quivi.\n\nqui si nuovi, e se tu n\u00f3n rispondi\ndi nostra via, restammo in su un pi\u00e0no\nsol\u00ecngo pi\u00f9 ch\u00e9 strade per diserti.\n\np\u00f2i disse: pi\u00f9 pensava maligna ' mai\ndi compagn\u00eca ver me ne da l'onda bruna\ns\u00f3tto la qual tu su per l\u00f9ngo 'l fiume\n\ndi n\u00f2va p\u00e9na d\u00f9nque per la lungi,\nper farti de la s.u.a. v\u00f2glia con\n\u00e0nzi 'l frati m\u00eco fatto; ch'or mi pia\n\nqui si nuota altrim\u00e9nti ch\u00e9 n\u00e9l serchio!\nper\u00f2, se tu s\u00f2l n\u00f3n se' la tua ragi\u00f3ne\ndi quella r\u00f3ma ch\u00e9 'n l\u00f9i pr\u00ecma viva.\n\np\u00f2i giunti f\u00f9mmo a l'angel benedetto,\nc\u00f3n la m\u00eca d\u00f2nna volse 'l s\u00f9o cost\u00e8i\na ricominci\u00f2: t\u00f9tto convegno.\n\nse tu guardi qu\u00e9l ch'io ti reo diviso\nper alc\u00f9n v\u00e9ro ch\u00e9 'l qu\u00e0le altr\u00f9i impronti,\nqu\u00e9sto ti piace, s\u00ec ch\u00e9 di parlare.\n\ns'elli \u00e8 ch\u00e9 s\u00ec t\u00f2sto r\u00e0de \u00e8 contratta\nch\u00e9 si conduce, n\u00f3n sarebbe lor spiace,\nche' l'arco t\u00f9o s\u00e0nto ch'ogne c\u00f2sa raggia.\n\nsarebbe sustanza, se n\u00f3n \u00e8 questo:\n",
        "temp_0.8": "\n\u00e0hi qu\u00e0nto a dir qual \u00e8ra \u00e8 c\u00f2sa d\u00f9ra\nn\u00f2va scender gi\u00f9 n\u00e9l v\u00ecso mi raccosta:\ns\u00ec ch\u00e9 la v\u00ecsta m\u00eca \u00e8 t\u00e0nto civi.\n\ne quella n\u00f3n rispuose cr\u00ecsto al s\u00f9o fero\nc\u00f3n le s\u00f9e parole, facce pi\u00f9 tardo,\ns\u00ec ch\u00e9 dal v\u00ecso t\u00f9o v\u00ecnco il valore.\n\nma voi prendete l'esca, s\u00ec ch\u00e9 'nse\nde la m\u00eca gl\u00f2ria e d\u00e9l m\u00f3nte palude,\nbili 'l qual si fece, e s\u00ec n\u00f3n di\n\nil qual se 'l ciel ch\u00e9 cotal si ricor\nd\u00e9l t\u00f9o raggiasse, c\u00f3me s\u00e0nza fociva,\ntal ch\u00e9 per t\u00f9o si ted\u00e9re andar per soggia.\n\nond'io a lui: domandal tu \u00e0ncora lumi,\ndicean: perche' mi s\u00eca ti rispondo,\ne n\u00f3n so che, se l\u00f2co m'\u00e8 propoco.\n\nio n\u00f3n so se 'ntendi, ne' m\u00eco t\u00e0nto\nlo 'ntender t\u00f9o per t\u00f9o volger bea?\nperche' io n\u00f3n parlo n\u00f3n si posson l'offizio\n\nf\u00e0tto riconosco alcun; ma s'a voi pia\ns'anima parl\u00e0rir \u00e8 qui tra s\u00ec dolciti,\nch\u00e9 'l piacer l\u00f3ro un piramo a te \u00e0ltona.\n\no d\u00f3lce padre, d\u00ec, qu\u00e0le offensi\u00f3ne\nsi p\u00f9rga qui n\u00e9l g\u00ecro d\u00f3ve semo?.\ncos\u00ec li dissi; e 'l d\u00f3lce convergo.\n\n\u00e0ncora \u00e8ra qu\u00e9l popol gi\u00f9 creder s\u00f3le\ntuoi concetti sarebbero espressi,\nma perche' 'l t\u00e8mpo m\u00eco segnor mi cosse\n\na te priego, ch\u00e9 gi\u00e0 m\u00e0i n\u00f3n sazia\na t\u00e0nto grazia, se n\u00f3n si vaneggia\ndi quella per darti ch\u00e9 n\u00f3n ti ha poco\n\ndal t\u00e8mpo m\u00eco segnor, ch\u00e9 si ricor\nal m\u00e8zzo 'l s\u00f9o parlar distrettamente,\nch\u00e9 s\u00f3tto i mie' piedi un s\u00e9gno e pi\u00f9 partito.\n\nla m\u00e9nte innamorata, ch\u00e9 donnea gioco,\nvolgendom'io c\u00f3n li etterni gemelli,\ntutta m'apparve da' colli a le foci gravi.\n\np\u00f2scia rivolsi li \u00f2cchi a li \u00f2cchi belli\ndi l\u00e0 dal sonno i miei p\u00e0ssi radiso,\ne di vederlo chinare, e fu tal \u00f3ra\n\nch'i' mi rivolsi d'ammirazion l\u00f9i pi\u00e8no\nal bu\u00f2n virgilio, ed \u00e9sso mi rispuose\nc\u00f3n le s\u00f9e parole parver di siede.\n\nqu\u00e9sti n\u00f3n m'\u00e8 a me; ma qui rispuose\nm\u00eca risp\u00f3sta cos\u00ec mi prevenne c\u00e0rca\ne per altrim\u00e9nti 'ncontrovar la vita.\n\nper\u00f2 ch\u00e9 'l s\u00f2l ch\u00e9 v'allum\u00f2 e arse,\nch\u00e9 tu dubi, n\u00f3n vieni a te ne conve,\ndi ch\u00e9 la divina pode, o \u00e8 l'offese\n\nf\u00e0tta fut\u00f9ro per tutte mal partita;\ns\u00ec che, c\u00f3me vedi, ancor n\u00f3n m'abbando\nlo tr\u00f2ppo dimanda, e ch\u00e9 'l ciel vede\n\nal t\u00e8mpo m\u00eco parlar drizz\u00f2 li morta,\ndisse 'l maestro, ch\u00e9 mi fa ch\u00e9 qui ve\nci\u00f2 ch\u00e9 tu vuoli, ch\u00e9 conservi sani?.\n\nn\u00f3n \u00e8 s\u00e0nza cagion ch\u00e9 tu mi mostraro\nli \u00f2cchi di qua gi\u00f9 n\u00e9l m\u00f3ndo basso,\nma chi se' fa chi di qu\u00e9sta p\u00e0ce tue.\n\ncos\u00ec da qu\u00e9sta g\u00e8nte pr\u00e8go mi dipira\ns\u00ec ch\u00e9 la giust\u00eczia m\u00eca in t\u00e8rra ha t\u00f2lto\nlo qual n\u00f3n ha p\u00f2i potesti la risposta.\n\nancor ti pu\u00f2 n\u00e9l m\u00f3ndo render fama,\nch'ella vive, e l\u00f9nga v\u00ecta ancor aspetta\nse 'nnanzi t\u00e8mpo gr\u00e0zia a se' n\u00f3l chiama.\n\ncos\u00ec disse 'l maestro; e qu\u00e9lli in fr\u00e9tta\nle man distese, e prese 'l d\u00f9ca mio,\nond'ercule sent\u00ec gi\u00e0 gr\u00e0nde stretta.\n\nvirgilio, disse, inver' la qual si torse\nvede compagn\u00eca ver me si pente,\ndisse 'l maestro, ansando, i deli \u00f2cchi\n\nc\u00f3n le s\u00f9e parole poco' suoi conve\nal pi\u00e8 de la r\u00ecpa ch\u00e9 'l n\u00e0so in t\u00e8rra\ne tal, ch\u00e9 n\u00f3n parean men le regi\n\ndi ch\u00e9 dal secr\u00e8to s\u00f9o cos\u00ec compunta\nc\u00f3n la f\u00e0ccia di dio, qu\u00e0si smarrita.\nl'acqua ch'io la m\u00eca sorrisi d\u00e9l nito,\n\nmi disse: qu\u00e9l cons\u00ecglio ch\u00e9 tu mi ve\nch\u00e9 tu tenesti ne la v\u00ecta lieta,\nper\u00f2 ch\u00e9 s\u00ec mi c\u00e0ccia il l\u00f9ngo tema.\n\ntu vuo' saper chi \u00e8 in di\u00e8tro dolore\nch\u00e9 tu te ne va s\u00ece di s\u00e0vio c\u00f2sta\nper se' o ven\u00f9to a se' l\u00f9nga folta?.\n\npur ier matt\u00ecna le volsi le spalle:\nqu\u00e9sti la g\u00e8nte ch\u00e9 m'\u00e8 pi\u00f9 vapori;\nma n\u00f3n so ch\u00e9 per lo 'ncarco si spande.\n\ne 'l d\u00f9ca m\u00eco discese per la val\ndi qua dal ciel d\u00e9l ciel n\u00f2stro si scosta,\ne 'l pret\u00e8re e 'l ciel discese converse;\n\ne qu\u00e9l ch\u00e9 fe' re al s\u00f2l ti portava pr\u00eca\nch\u00e9 'l s\u00f2l vagheggia or da coppa or da ciglio,\nio n\u00f3n m'accorsi d\u00e9l sal\u00ecre in ella;\n\nma perch'io v\u00e9ggio la par\u00f2la sincera,\nc\u00f3me fa, se tal gi\u00f9di l\u00e0 m'\u00e8 questa?\ns'io n\u00f3n avessi dir pi\u00f9 ne' maggior pena.\n\nvedi c\u00f3me l'ha f\u00e0tta di fi\u00e0mma fell\u00e0\nper ch\u00e9 la divina fi\u00e0mma \u00e8 agoverso,\nch\u00e9 f\u00eca men paia il mal ch\u00e9 n\u00f3n si face.\n\nla f\u00e0ccia m\u00eca cos\u00ec la pi\u00f9 di r\u00e0glia\nver\u00e0ce amor ch\u00e9 tal fr\u00f9tto \u00e8 di grazia,\ne ch\u00e9 fu contenta la mia, ch\u00e9 giace.\n\nquesti, padre, ch\u00e9 d\u00e9l t\u00f9o ret\u00e0ggio\n",
        "temp_0.9": "\n\u00e0hi qu\u00e0nto a dir qual \u00e8ra \u00e8 c\u00f2sa d\u00f9ra\ngi\u00f9 per l'altrui, s\u00ec ch\u00e9 ver n\u00f3n si via,\np\u00f2i se 'l f\u00f9mmo d\u00e9l pantan n\u00f3l ti nasco\n\nne' soler\u00f2 'l c\u00e0rro s\u00f3vra 'l mortal \nsu per la c\u00e0rne d'adamo \u00f3nde si vegna\nal montar s\u00f9, c\u00f3ntra s.u.a. voglia\n\ndisparmente ancor li \u00f2cchi a li \u00f2cchi caro.\ndopo 'l d\u00f9ca m\u00eco le p\u00e9nne persone,\npi\u00f9 \u00e8 tal, ch\u00e9 'l cammin\u00e0re onesto.\n\ned el mi disse: qu\u00e9lli \u00e8 da c\u00f9i\ns'aggiugne d\u00e9l ciel, c\u00f3me f\u00f2sse diffuso.\ne n\u00f3n so che, s\u00ec n\u00e9l cammino, a'ra\n\na ch\u00e9 cos\u00ec la m\u00eca ragion n\u00f3n cheggia\nm\u00f3lto sar\u00e0 di mal, ch\u00e9 n\u00f3n sarebbe,\nse n\u00f3n ch\u00e9 'l d\u00e9tto t\u00f9o voler t'ami;\n\nche' la m\u00eca par\u00f2la disisa volesse,\nla b\u00e8lla d\u00f2nna donna, e per\u00f2 fr\u00f9tto\ndi se' lasciando orribili dispregi!.\n\ne io: bu\u00f2n duca, n\u00f3n tegno rip\u00f3sto\na far ci\u00f2 ch\u00e9 tu se' in se' risposto,\ns\u00ec ch\u00e9 la m\u00eca sent\u00e8nza n\u00f3n mi sazia.\n\nond'io: maestro mio, or ti rispondesti,\nio ti conosco, che' n\u00f3n soccorre scarso,\nper altrim\u00e9nti tu sar\u00f2 l'uom felice?.\n\ned elli a me: nessun m'\u00e8 f\u00e0tto oltraggio,\nse qu\u00e9i ch\u00e9 l\u00e8va qu\u00e0ndo e c\u00f9i li piace,\npi\u00f9 \u00e8 la ragion d\u00e9l m\u00f3ndo ha sortita.\n\nma perche' pi\u00f9 \u00e8 da l'ovra ch\u00e9 ciglia?\ncos\u00ec \u00e8 germin\u00e0to qu\u00e9sto m\u00f3ndo\nc\u00f3me chi \u00e8, per salir per consunzio.\n\nn\u00f3n si \u00e8st d\u00e0re pr\u00ecmum motum esse,\no l\u00f9ce per me st\u00e9sso f\u00e0re a lui,\no per altrui, s\u00ec ch\u00e9 n\u00f3n si sarebbe.\n\nse tu riguardi qu\u00e9l ch\u00e9 si reverenti\na la m\u00eca morte, ch\u00e9 n\u00f3n ti farebbe\na tal dis\u00eco convien ch\u00e9 tu per lei,\n\nacci\u00f2 ch\u00e9 tu per m\u00eca narrai sazia,\nma per la m\u00eca virt\u00f9 ch\u00e9 n\u00f3n per lei,\nacci\u00f2 ch\u00e9 tu vuoli udir, perch'io l'ho v\u00ecsto\n\ns\u00e8mpre l'amor ch\u00e9 pot\u00e8nza di forese;\nper ch'io divenni sp\u00ecrto che, per te st\u00e9sso\nn\u00f3n in parlare, \u00e8 tr\u00f2ppo forando, gra\n\nch\u00e9 la v\u00f3ce tua sicura, s'ella p\u00f9gna\ndi veramente, al qu\u00e0le ha di questo,\nperche' s\u00eca 'l s\u00f3le amor n\u00f3n \u00e8 insuso.\n\nper\u00f2 ch\u00e9 'l l\u00f2co u' fui a viver posto,\ndi gi\u00f3rno in gi\u00f3rno pi\u00f9 di b\u00e8n si spolpa,\ne a tr\u00ecsta ru\u00ecna par disposto.\n\nor va, diss'el; ch\u00e9 qu\u00e9i ch\u00e9 tu n'ha \nvegg'io a c\u00f3da d'una bestia tr\u00e0tto tr\u00e0tto\ninver' la v\u00e0lle \u00f3ve m\u00e0i n\u00f3n si spanda.\n\nla bestia ad ogne p\u00e0sso va pi\u00f9 ratto,\ncresc\u00e8ndo sempre, fin ch'ella il percuote,\ne la pi\u00f9 sar\u00e0 di vilt\u00e0 di fosura.\n\nor sarebbe in te fu la v\u00f3ce d\u00f9ra\npi\u00f9 com'om ch\u00e9 va, ch\u00e9 sa m\u00eca per fede\nne' salir potier, c\u00f3me 'l ciel suole.\n\ne se tu guardi 'l princ\u00ecpio di tosca\nt\u00e0nto stare, ch\u00e9 n\u00f3l so ti riscoss'io.\nsubitam\u00e9nte ch\u00e9 'l p\u00f2rco l'ali, pensava\n\nfatti per lo 'nferno qua gi\u00f9 ti fuoro\nla m\u00eca ragion mi fece intr\u00e0ta aperta,\ne 'l d\u00f3lce suon de l'angoscia forannicchia.\n\nla f\u00e0ccia m\u00eca \u00e8 di t\u00f9tto il l\u00e9gno n\u00f2do\nch\u00e9 'l m\u00f3ndo \u00e8 l\u00f9nga v\u00ecso n\u00f3n sofferta\nper ch\u00e9 'l maestro disse: or vedi,\n\npensa col\u00f9i ch\u00e9 d\u00e9l cammin si mova:\nche' la divina giust\u00eczia li sprona\ns\u00ec ch\u00e9 la t\u00e9ma si volve in disio.\n\nqu\u00ecnci n\u00f3n p\u00e0ssa m\u00e0i \u00e0nima buona;\ne per\u00f2, se caron di te si lagna,\nb\u00e8n vederai c\u00f3me 'l cammin prego.\n\ne 'l d\u00f9ca m\u00eco discese per confondo\nch\u00e9 l'una de la fr\u00f3nte de l'altissima;\ne quella \u00e8 chi ch\u00e9 l\u00e0 s\u00f9 cr\u00ecsto ha?\n\ne 'l s\u00e0vio m\u00eco ingegno mar s\u00ec com'io.\n\n\nla f\u00e0ma ch\u00e9 la vostra chi\u00e8sa vagheggia\npr\u00eca ch\u00e9 sia, a gu\u00ecsa di fanci\u00f9llo\npiangendo se' a pi\u00e8tro d\u00e9l ciel soggiorno!.\n\ndi quella v\u00ecta cos\u00ec mi fu cagi\u00f3ne\nparer mi fece in volgermi al s\u00f9o dove;\np\u00f2i ch'era per lo 'nferno dota labbia!.\n\no d\u00f3lce padre, ass\u00e0i \u00e8 chi di\u00e8ce\ncos\u00ec orai; e quella c\u00f9i t\u00e9ma dura,\nse tu da confessi, e tu perche' mi \n\n\u00e0nzi m'assi ne la pr\u00ecma mi giunse,\nmi dirizz\u00f2 l'arte mie s\u00ec arte;\nma la m\u00eca virt\u00f9 sarebbe in te retro.\n\nse la m\u00eca par\u00f2la di t\u00e0nto b\u00e8lla\nti convene 'l conforto a qu\u00e9l ch'i' dico,\nch\u00e9 tu vedesti qu\u00e0nto 'l m\u00f3ndo s'infiora.\n\ned elli a me: d\u00e9l be\u00e0to conc\u00eclio\nti compriego, se n\u00f3n sarebbe notri\nci\u00f2 ch\u00e9 tu vuoli, ch\u00e9 conservi sanire'.\n\ne io a lui: dimostrami e dichiara,: qu\u00e0ndo\ntu mi fa ch'i' ti s\u00ece dica contento;\nvedi ch\u00e9 fier li denti a l'altra grotta.\n\no tu ch\u00e9 leggi, udirai nu\u00f2vo ludo\nciascun da l'altra c\u00f2sta li \u00f2cchi volti aperti\ndi compagn\u00eca ad ogne mover d'anca.\n",
        "temp_1.0": "\n\u00e0hi qu\u00e0nto a dir qual \u00e8ra \u00e8 c\u00f2sa d\u00f9ra\nper veder la divina s\u00e9lva tanta;\nne' s\u00ec ch'io n\u00f3n lo 'ntesi, ne' compresi\n\nche' n\u00f3n potea fotin me pensando?'.\ncos\u00ec s\u00e9n va, spiriti c\u00f3me forati in v\u00f2glia\ndi ch\u00e9 la sper\u00e0nza mi consenti;\n\ndisse: \"che? per satitisti n\u00f3n ti \nma qu\u00e9i ch\u00e9 ti fanno d\u00f2 se' la cima,\nperche' nostra c\u00f3lpa \u00e8 a la tua fam\u00ecglia\n\nn\u00f3n pur per lo p\u00e9so de la far giova\nde la f\u00e0ccia di dio, ma n\u00f3n volgi?.\ncos\u00ec n\u00f3n so 'l maestro qu\u00e9sti corpini;\n\ne disse: vedi ch\u00e9 n\u00f3n s\u00f2n da qu\u00e9sta\ne per altrim\u00e9nti fan di t\u00e0nto rota,\nch\u00e9 n\u00f3n curasse di m\u00e9ttere in arca.\n\nper\u00f2 ricominciai: t\u00f9tti qu\u00e9i ch\u00e9 tu scandi\nd\u00e9l t\u00f9o dis\u00eco ch\u00e9 f\u00f2rte fu condanni;\nma ch\u00e9 n\u00f3n potea da bu\u00f2n d\u00e9gno rico,\n\nper\u00f2 ti priego, d\u00f3lce p\u00e0dre sazio,\ns'a la m\u00eca m\u00e9nte d\u00e9l s\u00f9o ti risponde\nal qu\u00e0le \u00e8 f\u00e0tta la tocc\u00e0ta norma.\n\nne l'orribil di d\u00eco cos\u00ec \u00e8 cotanto\nch\u00e9 'l s\u00f9o contr\u00e0rio s\u00f9o concelante;\ns\u00ec ch\u00e9 per\u00f2 n\u00f3n \u00e8 bu\u00f2n vivo sarebbe.\n\nvedi quanta g\u00e8nte ch\u00e9 piange e diletta,\nn\u00f3i stato; e qu\u00e9sti de la tua pervenne\npi\u00f9 c\u00f3rte 'l ciel, c\u00f3me v\u00ecta sospetta.\n\ncos\u00ec virt\u00f9 mia, perche' s\u00ec ti ragiona\na le cose ch\u00e9 'l s\u00f9o dis\u00eco confessi\npur ch\u00e9 la fi\u00e0mma ch'al s\u00f3mmo si canta.\n\ne c\u00f3me si va per \u00e0mbo le strade,\nper le quali, accolte, acci\u00f2 ch\u00e9 vedi\na qu\u00e9l ch'accese amor tra l'omo e 'l fonte.\n\ns\u00f9bito s\u00ec com'io di lor m'accorsi chiesi,\nquelle lettere ch\u00e9 'l cor di n\u00f3i si stra\nquelle ch\u00e9 per t\u00e9ma ha p\u00f2co lo risso.\n\ned elli a me: nessun m'\u00e8 f\u00e0tto \u00e0ncora\nfregia s\u00f9so in te, s\u00ec f\u00e0tta lasciasse,\npar\u00e8a d\u00e9l s\u00f9o ciel, s'alcuna grotta.\n\ne c\u00f3me pi\u00f9 e m\u00e9co l'altro ha p\u00e0rte\nriv\u00f2lto ad esse, e veder l'ombra ch\u00e9 'l c\u00e0nto\nper qu\u00e9l veder, benche' io fossi noi.\n\nv\u00e9ro \u00e8 ch'i' vidi, e t\u00e0nto div\u00ecno\na le s\u00f9e ragion parve gi\u00f9 di carca,\nch\u00e9 'l s\u00f9o per cant\u00e0gno e merti commise.\n\nf\u00e0tto m'hai lieto, e cos\u00ec mi fa chia\nci\u00f2 ch\u00e9 'l d\u00e9tto t\u00f9o s\u00e9gno n\u00f3n discerno\na la m\u00eca d\u00f2nna ch\u00e9 dirizz\u00f2 lo spiro\n\nal t\u00e8mpo m\u00eco col\u00f9i ch\u00e9 t\u00f9tto sazia,\ndisse: mal fu lat\u00eczia m\u00eca l'esser buia,\nne la mil\u00eczia s.u.a. discerna il cr\u00e9to\n\ns\u00ec m'accors'io ch\u00e9 'l f\u00f2co \u00e8ra lat\u00ecno\na l'orazion mia, ch\u00e9 de li \u00e0ltri grave\nn\u00f3n ti p\u00f2ria menar da me altrove luce.\n\ne se la m\u00eca ragion n\u00f3n ti disfama\ns\u00ec ch\u00e9 'l l\u00f9me d\u00e9l ciel n\u00f3n si spazia,\ne per udirti s\u00f3pra me n\u00f3n ha pace.\n\ne se la st\u00e9lla si cambi\u00f2 e rise,\nqual ti fec'io ch\u00e9 pur da m\u00eca nat\u00f9ra\ntrasmut\u00e0bile s\u00f2n per tutte guise! .\n\nc\u00f3n t\u00e0nta dig\u00e8dia in alc\u00f9n loco: figlio:\nb\u00e8n mi lascer\u00f2 m\u00e0i tua gu\u00e0rda favelle,\ntu n\u00f3n vedi c\u00f3me ch\u00e9 'l comduca gente\n\nn\u00e9l m\u00f3ndo s\u00f9o cos\u00ec parl\u00e0ndo cinta,\nch\u00e9 la v\u00ecsta \u00e8 contratta ch\u00e9 la costa.\nla f\u00e0ccia tua, n\u00f3n \u00e8 s\u00f9o v\u00ecsto corre\n\npi\u00f9 ch\u00e9 da l'universo de la dif\u00e0lta\nsi fa d\u00e9gno de la pr\u00ecma par\u00e8a ghiotto\nda lor vederla n\u00e9l m\u00f3ndo e ch\u00e9 sogna.\n\nio n\u00f3n so se pi\u00f9 f\u00f2sse pi\u00f9 di foco\nma per qu\u00e9l ch\u00e9 sov\u00e8rchio la ved\u00f9ta\nvedea io te segnata in su la m\u00eca vista.\n\nqu\u00e0le 'l falcon s\u00f3le in su la terra,\nma per n\u00f3i pa\u00f9ra la g\u00e8nte sconcia,\ns\u00ec ch\u00e9 n\u00f3n so perder s\u00f3pra 'l seguiva.\n\ncos\u00ec per li gr\u00e0n savi si concorda,\ndisse 'l maestro; ed elli stessi s'accusto\nveder beatr\u00ecce fu\u00f2r d\u00e9l d\u00f9ca mio.\n\nc\u00f3me 'l m\u00e8zzo me d\u00e9l cielo, a c\u00f9i\ndisse: o tu ch\u00e9 se' tu s\u00ec smarrito?\n\u00e0nima f\u00eca a ci\u00f2 pi\u00f9 di me degna:\n\nc\u00f3n t\u00e0nto dil\u00e8tto ci\u00f2 ch\u00e9 la 'mprenta\ndi qua, di l\u00e0 gi\u00f9 si piange mai;\nma per col\u00f9i ch\u00e9 siede \u00e0lto dopo!.\n\nvedi c\u00f3me l'ha dritte v\u00e8rso 'l cielo,\ntrattando l'aere c\u00f3n l'etterne penne,\nch\u00e9 n\u00f3n si mur\u00f2 n\u00e9l sec\u00f3ndo regno;\n\ne qui per f\u00f2rza di stupor n\u00f3n biece,\nguardando pur c\u00f3n qu\u00e9sto tr\u00ecsto c\u00f3n sorte,\nc\u00f3me dicesse a d\u00eco chi \u00e8 da se' pace\n\nch\u00e9 la g\u00e8nte ch\u00e9 da tutte \u00e8 molte;\ned elli avea venir d\u00e9l tr\u00ecsto di martiri\nper la contr\u00e0ria s\u00f9o m'\u00e8 incontrato.\n\na qu\u00e9sto inv\u00ecto vegnon m\u00f3lto radiso:\no g\u00e8nte umana, per volar s\u00f9 nata,\nperche' a p\u00f2co v\u00e8nto cos\u00ec cadi?.\n\nmenocci \u00f3ve la r\u00f2ccia \u00e8ra tagliata;\nqu\u00ecvi \u00e8 la r\u00f2ccia s\u00ec ch\u00e9 n\u00f3n \u00e8 queta\ndi tal, ch\u00e9 'ntendi s\u00f9 n\u00f3n si vaglia\n\ndal princ\u00ecpio d\u00e9l cader di n\u00f2va torta,\n",
        "temp_1.1": "\n\u00e0hi qu\u00e0nto a dir qual \u00e8ra \u00e8 c\u00f2sa d\u00f9ra\ntal, ch\u00e9 da se' \u00e0nima n\u00f3n \u00e8 buona\nne' da qual figliuol, ne' io \u00e8 cogna?\n\nn\u00f3n \u00e8 s\u00e0nza cagion l'andare al cupo!\nchi siete voi ch\u00e9 s\u00eca gi\u00e0 la sprona,\ns\u00ec ch\u00e9 'l d\u00f9ca m\u00eco \u00e8ra s\u00e8mpre n\u00f3n t'adocchia\n\ne 'l d\u00f9ca m\u00eco \u00e8: o tu ch\u00e9 \npafreddo vai per l'aere a cu' io ti fissi,\nrispuose 'l m\u00eco maestro a lui, pur t\u00f2sto\n\na quella f\u00f3ce ha elli or dr\u00ectta l'ala,\nper\u00f2 ch\u00e9 s\u00e8mpre qu\u00ecvi \u00e8 s\u00ec a messo,\nch\u00e9 'l s\u00f3le avea tutta li \u00f2cchi aperta.\n\npi\u00f9 n\u00f3n ti dovea gravar la montagna,\nper ch'io, ch\u00e9 la m\u00eca f\u00e0ccia n\u00f3n pu\u00f2 i\na risponder gi\u00f9 n\u00e9l m\u00f3ndo n\u00f3n sa.\n\nond'io, ch\u00e9 s\u00f3lo inn\u00e0nzi a me n\u00f9lla s'aombra,\nn\u00f3n ti maravigliar s'io la rincalzo\npi\u00f9 ch\u00e9 n\u00f3n ti celer\u00e0 l'esser pi\u00f9 bella,\n\nma chi, per n\u00f9lla volont\u00e0, dirmi.\ncol\u00f9i ch\u00e9 la m\u00f2rte m\u00eca men fu sorte,\ndisposando per v\u00eca su ch'a lor n\u00f3n torre\n\nse la f\u00e0ccia tua di mem\u00f2ria rest\u00e0re\nper la c\u00f3lpa tua conf\u00f2rta si smarria,\nch'a n\u00f9lla 'nvidia pr\u00ecma dispogliata labbia.\n\n\u00e0mbo vegnon di l\u00e0 \u00f3nde 'l preg\u00e0to\nma, per color ch\u00e9 se' ne la risposta,\nma per trattar d\u00e9l b\u00e8n ch'i' vi dolente,\n\nditemi si tace; e 'l bu\u00f2n maestro,\nche' 'l t\u00f9o voler di n\u00f3i si saziava,\ns\u00ec ch\u00e9 dal v\u00ecso t\u00f9o v\u00ecnco il vapore.\n\nn\u00f3n \u00e8 nu\u00f2va l\u00f9me s\u00e0nza m\u00e8zzo nostra:\ntanto, ch\u00e9 d\u00e9l ciel n\u00f3n \u00e8 f\u00e0tto valo,\npensa la succession, quinci, \u00e8 inteso\n\nlet\u00eczia \u00e8 d\u00e9l s\u00f9o qu\u00e9sto contr\u00e0rio d\u00ec\npi\u00f9 al montar per lo r\u00e0ggio s\u00e0ngue lui,\ns\u00ec ch\u00e9 col\u00f9i n\u00f3n incresce a me, e ardo!.\n\nor sai tu d\u00f3ve e qu\u00e0ndo qu\u00e9sti amori\nfu degna di ven\u00ecre a qu\u00e9sta risposta,\nch\u00e9 la divina virt\u00f9 n\u00f3n intender to?.\n\ne 'l d\u00f9ca m\u00eco di ch\u00e9 ti parlare\nper alcuna virt\u00f9, in \u00e0nima condita,\nmi disse, t\u00e0nto ch'a b\u00e8ne \u00e8 trasc\u00f3rsa.\n\nn\u00f3n ancor ti pu\u00f2 di l\u00e0 m\u00e0la viva,\nma per trattar d\u00e9l b\u00e8n ch'i' vi trovai,\ndir\u00f2 e 'l l\u00f9me m\u00eco tra t\u00e0nto s\u00e9nno\n\nch\u00e9 per l'effetto de' suo' m\u00e0i pensieri,\nfidandomi di lui, io fossi pr\u00e9so\na l\u00f9i lasc'io, che' n\u00f3n li sar\u00e0n forti.\n\nne' per \u00e0ltri beo per cu' io movo\nliberam\u00e9nte ci\u00f2 ch\u00e9 'l t\u00f9o dir priega,\nti fermati anco, ancor vo' ch\u00e9 ti pene.\n\nvedi ch\u00e9 cose m\u00eca t\u00e0nto contenta\nn\u00e9l t\u00f9o cons\u00ecglio ch\u00e9 spirar n\u00f3n possenti,\nse tu da veder tr\u00f2ppo n\u00f3n \u00e8ra meco.\n\nse per disizion ch\u00e9 fi\u00e0mma n\u00f3n si puote\nci\u00f2 ch\u00e9 'l d\u00e9tto t\u00f9o s\u00e0nto teconio,\nd\u00f3lce p\u00e0dre mio, s'altri n\u00f3n \u00e8 mena;\n\nma perche' tu veggi voi vostra latera\nda l'omero de la g\u00e8nte ch\u00e9 mi mostra,\nqu\u00e0ndo la m\u00e9nte tua, e gi\u00f9 n\u00f3n ti puo\n\nse tu guardi qu\u00e9l ch\u00e9 si reverenti\na la m\u00eca d\u00f2nna ch\u00e9 in s\u00f9 ti sazia\nl'esser di t\u00f9tto s\u00f9o perche', \u00e8 degno?\n\ne c\u00f3me sa chi s\u00f2n s\u00e0nza si dim\u00f2ra\nla m\u00eca compagn\u00eca cost\u00f9i \u00e8 ne nostra,\ns\u00ec ch\u00e9 t\u00e0rdi per \u00e0ltri si ricrea.\n\ndi quella v\u00ecva l\u00f9ce \u00f3nde s'infiora\n'l dar di col\u00f9i ch\u00e9 qui si rimira,\nper la m\u00eca virt\u00f9 ch\u00e9 t\u00f9tto \u00e8 contento\n\ndi qu\u00e9sta l\u00f9ce ch\u00e9 vid'io gi\u00f9 intenti\nper alc\u00f9n gi\u00f9, di fu\u00f2r d\u00e9l d\u00f3lce v\u00ecvo\ncot\u00e0nto ch\u00e9 la ved\u00f9ta n\u00f3n pu\u00f2 diviso.\n\ne 'l v\u00e9ro in ch\u00e9 si p\u00f2rta pi\u00f9 persona\ndi m\u00e8zzo 'l ciel cacci\u00e0to capricorno,\ns\u00ec ch\u00e9 tagliava \u00e8 qu\u00e9sto c\u00f3me lor vano\n\ne la f\u00e0ccia m\u00eca n\u00f3n cadeva al marco:\ntant'era gi\u00e0 m\u00e9co di l\u00e0 da n\u00f3i dritto,\nlo qual suoni la v\u00ecsta \u00e8 color consorti\n\na gu\u00ecsa d'uom ch\u00e9 'n d\u00f9bbio si raccerta\ne ch\u00e9 m\u00f9ta in convenia di lor la 'mpasca\nch\u00e9 'l m\u00f9so inn\u00e0nzi su l'error de' corti.\n\ncos\u00ec disse il m\u00eco duca, e io c\u00f3n l\u00f9i\nvolgemmo e 'l d\u00f9ca mio, e diss'io mi frasca\nlo m\u00eco disse: mal pensa ch\u00e9 tu mi \n\nvedi ch\u00e9 n\u00f3n ha f\u00ecne e se' di tenuto\nal qu\u00e0le ha f\u00e9rmo 'l m\u00f3ndo pi\u00f9 ago,\n\u00e0nima ten de la tr\u00ecsta ch\u00e9 tu solve.\n\nn\u00f3n cors\u00e8 m\u00e0i s\u00ec t\u00f2sto f\u00e0tto s\u00e0le\na le cose ch\u00e9 furon s\u00ec fatte felle,\nche, c\u00f3me vedi, ancor n\u00f3n m'abbandona.\n\na le quai p\u00f2i se tu vorrai salei\nal t\u00f9o pensier di qu\u00e9l ch\u00e9 tu chiedi,\nch\u00e9 'l piacer mio, perche' s\u00ec ti gioi.\n\nn\u00f3i ci volgiam c\u00f3i principi celesti\nd'un g\u00ecro e veder de la f\u00f2ssa ch\u00e9 stanca,\ne 'l m\u00e8zzo ch'era di ciascuna spalla,\n\ne gi\u00e0 vedea gi\u00e0 m\u00e0i chi si vivace\nd\u00e9l c\u00e0rro stanco, a la schi\u00e8ra si parte\ndi c\u00e0po ten r\u00e8tro a se' stessa le regi.\n\nl'anima d\u00e9l t\u00f9o r\u00e0ggio \u00f3nde si volse\n",
        "temp_1.2": "\n\u00e0hi qu\u00e0nto \u00e8ra l\u00f9nga e poder sa;\nma per \u00e9ntro facean ch'al riguardar l'ali,\ns\u00ec ch\u00e9 la f\u00e0ccia m\u00eca n\u00f3n \u00e8 risposta.\n\nvedi c\u00f3me l'ha dritte v\u00e8rso 'l cielo,\ntrattando l'aere c\u00f3n l'etterne penne,\nch\u00e9 da valor n\u00f3n vuol, per pi\u00f9 farti.\n\ne se qui dal pr\u00ecmo f\u00f2co s'armina,\ncominci\u00f2 elli a dire, e salir ti move\ndi qu\u00e9l ch\u00e9 l'ha qua s\u00f9 n\u00f3n cot\u00e0nza cura,\n\ns\u00ec grid\u00f2: nessun \u00e8 desse ne' gravi,\nrispuos'io lui, voi n\u00f3n sareste \u00e0ncora\ndeh, se n\u00f3n c\u00f3me gi\u00f9 per s\u00f2l vendetto;\n\ne se la st\u00e9lla si desse t\u00e0nto l\u00f9ce\ndi ch\u00e9 'l ciel vedete st\u00e9sso alz\u00f2ra\nl'antico d\u00e9l t\u00e8mpo e la state; ond'io paleso\n\nn\u00f3n so chi tu se' ne' m\u00eca n\u00f2tte lieta\nc\u00f3n l'ali aperte, ch\u00e9 s\u00f2l d\u00e9l s\u00f9o fatto;\ne la divina bont\u00e0 n\u00f3n ha man preso.\n\nper\u00f2 che, giunti, se d\u00e9l ciel ti rende\nl\u00f9ce d\u00e9l ciel dilettar v\u00e9ro e 'l tito,\ne ci\u00f2 ch\u00e9 in se' parlar n\u00f3n sazia vide\n\nper\u00f2 che, c\u00f3me d\u00e9l color ch\u00e9 crea,\nper ch\u00e9 'l m\u00f3ndo mortal per s\u00e8mpro vive,\ncos\u00ec \u00e8 germin\u00e0to qu\u00e9sto fiore.\n\nqu\u00ecnci rivolge la d\u00f2nna ch\u00e9 pr\u00eca l\u00e8zia\nper la ver\u00e0ce fede, cos\u00ec 'l fatt\u00f3re\na la qual s\u00e0nta in circo circunferenti.\n\ne c\u00f3me 'l volge e \u00e0ltro circunferente,\ncos\u00ec fa 'l cielo, e l'ultima r\u00f2sa\nse n\u00f3n per da la s.u.a. sc\u00e0la \u00f3nde\n\ncos\u00ec vede di la c\u00f3rte si p\u00e0rte\ntante d\u00e9l ciel di se' chi far n\u00f3n sarebbe\na la giust\u00eczia di dio, ne l'interdetto.\n\ncos\u00ec qu\u00e9sta pal\u00f9te s\u00e0nta t\u00e8rra\nn\u00e9l n\u00f2stro l\u00f9me dilettor, ch\u00e9 'n udi\nor se ne va ne la ma io v\u00e9ggio quindi;\n\ne se d\u00e9l camm\u00ecno \u00e0ltro si discerne,\nche' dal voler di col\u00f9i crescer la sc\u00e0la\nsi move tutta quella lice,\n\nricominci\u00f2: t\u00f9tto ch\u00e9 'l m\u00f3ndo c\u00e9rchia\npi\u00f9 \u00e8 'l piacer di ch\u00e9 qui si corte,\nvedrai beatrice, ed \u00e9lla pienam\u00e9nte\n\nfrate, diss'io, ch\u00e9 vuo' tu pi\u00f9 volesse\nqu\u00e9i ch\u00e9 la m\u00eca distill\u00f2 \u00e8 pi\u00f9 spessa,\nfu degnata in se' orai; e sanz'esser urto.\n\nche', perche' n\u00f3n ti maravigliar pi\u00f9 vici\nla m\u00eca d\u00f2nna m\u00eca ch\u00e9 lo 'mpedico,\n\u00e8 da ch\u00e9 n\u00f9lla credi s\u00f2n le restizia.\n\nor accordia, e virgilio, \u00e0lto d\u00eco\nn\u00e9l s\u00f9o voler di col\u00f9i n\u00f3n intenta,\ntal ch\u00e9 f\u00eca n\u00e0to a ci \u00f2cchi tieni!.\n\nper ch'io a lui: se tu riduci a m\u00e9nte\nqual fosti meco, e qual io t\u00e9co fui,\nancor f\u00eca gr\u00e0ve il memorar presente pieta.\n\ndi quella v\u00ecta mi volse, e rispuose\nal s\u00f9o dis\u00eco conosciuto, ch\u00e9 qu\u00ecvi\nn\u00f3n so 'l parlare, ma di a l\u00f9i trascorta.\n\nlo ciel se tu pi\u00f9 t\u00f2sto n\u00f3n ti conce\nvedi ch\u00e9 la sper\u00e0nza \u00e8 nostra vita,\nn\u00f3n ti p\u00f2ria menar da l'altra probo.\n\nse tu se' s\u00ec accesti par di sali,\nma n\u00f3n vedi l\u00e0 ch\u00e9 la f\u00e0ccia \u00e8 bella\nne' di l\u00e0 chi 'l chiedea s\u00f9 t\u00e0nto te\n\nn\u00f3n so se ricordar ch'altra s\u00e0nza goma,\nch\u00e9 vive 'l c\u00e0rro d'elia al dipartire,\nqu\u00e0ndo i cavalli al ci\u00e8lo erti levorsi,\n\nch\u00e9 n\u00f3l potea s\u00ec c\u00f3n li \u00f2cchi seguiva\ndi qua, di l\u00e0 soccorrien c\u00f3n le m\u00e0ni\nqu\u00e0ndo 'l c\u00e0rro t\u00f9tto l\u00f3ro a le foglie.\n\ndi qua, di l\u00e0, di st\u00e0te venuti\nle m\u00e0ni in su l'erbetta, e li arruncigli;\ns\u00ec ch\u00e9 la t\u00e8rra n\u00f3n par\u00e8a lor vanto.\n\no d\u00f3lce padre, d\u00ec, qu\u00e0le offensi\u00f3ne\nsi p\u00f9rga qui n\u00e9l g\u00ecro d\u00f3ve semo?.\nvieni a veder la g\u00e8nte qu\u00e0nto s'ama!\n\nrispuose adunque: pi\u00f9 ang\u00f9ra in su si \u00e0nche\ndi qua, di l\u00e0 soccorrien c\u00f3n le sceme;\nch'el chi \u00e8 col\u00f9i da la ved\u00f9ta labbia.\n\no virt\u00f9 somma, ch\u00e9 per li empi giri\nmi volvi, cominciai, com'a te piace,\nparlami, e sodisfammi a' miei disiri.\n\nla g\u00e8nte ch\u00e9 per li sepolcri giace,\na la m\u00eca d\u00f2nna m\u00eca cos\u00ec, rispuose\nc\u00f3n la f\u00e0ccia di dio, chi n\u00f3n sarei \n\npier da me t\u00e0nto ch\u00e9 'ntender la tema\nde la c\u00e0rne d'anime ch\u00e9 tu mi fanno?\nperche' n\u00f3n vedre? per\u00f2 che' n\u00f3n siete?.\n\ned elli a me: t\u00f9tti quanti fu\u00f2r guerci;\ns\u00ec ch\u00e9 la v\u00ecta mia, ch\u00e9 di se' torse\ndal f\u00ecglio stesso, che, queste n\u00f3n s\u00f2n io\n\nn\u00f3n cors\u00e8 c\u00f3me tu qua s\u00f9 n\u00f3n vedi;\nma per ch\u00e9 'l dolor mi fe' alcuna f\u00ecne\na l'alto lavocere, ingr\u00e0do partere.\n\nch\u00e9 quella min\u00e0nzi queste parole carte\nper ch'io, acc\u00f2rto d\u00e9l s\u00f9o parlar ten l\u00f9me\nch\u00e9 dal s\u00f9o m\u00e8zzo 'n su lo 'ntelletto\n\nvoi prendete t\u00f9o voi ch\u00e9 s\u00eca l'amba\ns\u00e8mpre di fuor, c\u00f3me qu\u00e9l da l\u00e8i vede\nch\u00e9 si vuole, cos\u00ec ch\u00e9 qui \u00e8 professa.\n\ne c\u00f3me fu la m\u00eca m\u00e9nte s\u00ec b\u00e8lla\n",
        "temp_1.3": "\n\u00e0hi qu\u00e0nto a dir qual \u00e8ra \u00e8 c\u00f2sa d\u00f9ra\n\u00e9sta s\u00e9lva selvaggia e \u00e0spra e f\u00f2rte\nch\u00e9 n\u00e9l pensier rinova la paura!\n\ntant'\u00e8 amara ch\u00e9 p\u00f2co \u00e8ra pi\u00f9 morte\nper qu\u00e9llo ch\u00e9 crescer\u00e0 ch\u00e9 'l partire,\nrispuose, per la sper\u00e0nza \u00e8 'l vermo;\n\ne se tu guardi qu\u00e9l gr\u00e0n cos\u00ec ch\u00e9 fr\u00f9tto\nrispuose 'l maestro amor ch\u00e9 tu mi vedi;\nma qui \u00e8 bu\u00f2no c\u00f3n s\u00ec br\u00e8ve e arguto.\n\nvirgilio mi v\u00e8nia da quella b\u00e0nda\nde la p\u00e0ce pa\u00f9ra d\u00e9l s\u00f9o dito;\nma ch\u00e9 mi va dr\u00ecttar per la soglia.\n\ne se qui si dee ora, d\u00f3lce guida,\nvirt\u00f9, c\u00f3me di\u00e8tro ad \u00e9ssa corre straglia,\ndicendo: in v\u00ecva mio, qu\u00ecvi \u00e8 chiuso\n\nlo regnor, ch\u00e9 s\u00ec la f\u00e0ccia n\u00f9lla\ncia' io, che' la vostra per tel\u00eczia tanta\nla m\u00eca pers\u00f3na ch'\u00e8 m\u00e9co e n\u00f3n ha vede\n\ndal princ\u00ecpio d\u00e9l cader ch'\u00e8 pr\u00e9gno \u00e8 pr\u00e9gno\ndi ch\u00e9 si per \u00e0cqua \u00e8 in gi\u00f9sta voglia\na la qual tu sust\u00e0nza dici si faci.\n\nqu\u00e9sta miseria; ch\u00e9 qui \u00e8 t\u00e0nto va,\nch\u00e9 basti a render voi gr\u00e0zia per grazia;\nma qu\u00e9sto \u00e8 bu\u00f2n proposto, per tantore,\n\nch\u00e9 per mois\u00e8, per profeti e per salmi,\ndi qu\u00e9sta fi\u00e0mma s.u.a. in cura;\nma per la seguirla, in ch\u00e9 li 'nfriri\n\nde la m\u00eca vista; e per\u00f2 s'ella\nsi mosse, e la giust\u00eczia di si scerna\nc\u00f3me fa 'l ciel ve ch'a lor disarebbe.\n\nnat\u00f9ra s\u00ec fatta, ch\u00e9 'n altre r\u00e0ce\na voi, ch\u00e9 tal vedi l\u00e0 gi\u00f9 n\u00f3n resta\ndir\u00f2 ch\u00e9 'l m\u00f3ndo l\u00ec \u00e8 t\u00f9tto sofferta\n\nio cominciai: maestro, qu\u00e9l ch\u00e9 tu mi \ndi veder, benche' io fossi governa;\nma s\u00ec ch\u00e9 n\u00f3n so n\u00f3n \u00e8 lor procedo.\n\nqu\u00e9i s\u00f2no spirti, maestro, ch'i' odo?,\ndiss'io, \u00e8 ch\u00e9 l'angoscia di lor parte,\nper ch\u00e9 'l maestro acc\u00f2rto lo sospiro.\n\ne cheggiatendo l'un ver li d\u00f9e cozzi:\nqu\u00e9sti pu\u00f2 dar di qu\u00e9l ch\u00e9 tu 'l venese\ntraean di l\u00e0 gi\u00f9 trovar la gorfamaro.\n\nall\u00f3r disse: b\u00e8n puose biso far m\u00e0no\ne d\u00e9l s\u00f9o pensier rino; \u00f3nde n\u00f3n s\u00e0nza\nrestaron, se rallargati la tegna.\n\nli \u00f2cchi poeti a me st\u00e9sso far cristo:\ns\u00e0nza la qual per t\u00f9o n\u00f3n ti sazia,\ndov'io per me pi\u00f9 \u00f3ltre n\u00f3n dichiari.\n\ncos\u00ec si consonava, e io penso tocca,\nch\u00e9 'l pensar de la v\u00ecsta \u00e8 ch\u00e9 costa\ne ch\u00e9 n\u00f3n par\u00e8a s'era l\u00e0ico o cherco.\n\nqu\u00e9i mi sgrid\u00f2: perche' se' tu s\u00ec g\u00f2rdo\ndi riguardar pi\u00f9 me ch\u00e9 li \u00e0ltri brutti?\nper ch\u00e9 'l maestro mi disse: or pensa\n\nvedi ch\u00e9 n\u00f3n ti anci; ma s'io modo\nti fu\u00f2r di qu\u00e9llo in cepelago, a vesse\nm\u00e9ntre ch\u00e9 'l t\u00e8mpo s\u00f9o t\u00f9tto tien crude\n\ndi ch\u00e9 dal ciel ch\u00e9 'n tutt'i cerchi bianchi\nde la s.u.a. spondia, \u00f3ve conforma\ndovea la sec\u00f3nda l\u00f9i tr\u00e0rre guai,\n\no crudel, se tu se' \u00e0nima fuia.\npi\u00f9 f\u00f2sse la virt\u00f9 di tenebra stanchi,\nch'a l'alto lavostra statera n\u00f3n sien parvi.\n\nbeatr\u00ecce mi guard\u00f2 c\u00f3n la spada,\nche' n\u00f3n pur piedi e ten de le mie mani,\nper ch\u00e9 la m\u00eca m\u00e9nte pr\u00ecma n\u00f3n pu\u00f2 i\n\nregion ch\u00e9 'l t\u00e8mpo di t\u00f9tto il ciel volle\nmi fu detto; e qu\u00e9sto \u00e8 veradisfaccia\nlo 'ntender de la chi\u00e0ve v\u00ecta costa.\n\np\u00f2i cominci\u00f2: c\u00f2sa n\u00f3n \u00e8 ch\u00e9 s\u00e0nza\ndi s\u00e0nza 'l dolor ch'a se' mi satita,\ns\u00ec ch\u00e9 la v\u00ecsta m\u00eca \u00e8 f\u00e0tta corre.\n\ne vegno in p\u00e0rte \u00f3ve n\u00f3n \u00e8 ch\u00e9 luca\nch\u00e9 s\u00ec a la m\u00eca d\u00f2nna mi rispuose,\ne molte g\u00e8nte per vien ch\u00e9 qui n\u00f3n vada\n\ncos\u00ec mi disse il s\u00f2l de la s\u00e9te torta\ndi qu\u00e9l ch\u00e9 'l ciel veloce fen\u00f9ta qu\u00ecvi\ns\u00f3tto la g\u00e8nte ch\u00e9 per se' \u00e8 ricosta.\n\nor sai tu d\u00f3ve e qu\u00e0ndo qu\u00e9sti suoni;\ne ch\u00e9 la m\u00eca vita piange e discende,\nn\u00f3i fossimo al pi\u00e8 de l'alta torre, invore\n\nch\u00e9 da l'erba e da la fi\u00e0mma fu sospira\nmut\u00e0ta \u00e8 qu\u00e9sta g\u00f3la \u00f3ltre riprende:\nor \u00e8 f\u00e0tto la sembi\u00e0nza s.u.a.\n\nne l'arzia disposto, disse: pi\u00f9 vera,\nperche' al ciel, in ch\u00e9 la dimanda l\u00e8i\nf\u00eca men d\u00f3lce canz\u00f3ne e pi\u00f9 profonda.\n\ne se pi\u00f9 fu cost\u00ec, la cagion conta\nt\u00e0nto ch\u00e9 la s.u.a. semenza, gi\u00f9 \nnascendo, in qu\u00e9sto ci\u00e8lo udito;\n\n\u00f3nde la f\u00e0ccia m\u00eca \u00e8 t\u00e0nto fr\u00f9tto\ndi grazia, ch\u00e9 l'amor mi par ch'i' sento,\nd'entro le leggi tue chiavi s\u00ec fatto?.\n\ned elli a me: beatr\u00ecce n\u00f3n si conce\nse li \u00f2cchi miei da l\u00f9i fossero aversi;\ne qu\u00e0nto il t\u00e8mpo t\u00f9o da qu\u00e9l ciel chiami.\n\nc\u00f3me l'ha dritta da la c\u00f2sta queta,\nper veder lo spiriti c\u00f3me viemani;\ne di mat\u00e8ria gr\u00e0zia \u00e8 pi\u00f9 agota,\n\nch\u00e9 da qu\u00e9sta p\u00e0rte c\u00f3n virt\u00f9 m'asseta,\n",
        "temp_1.4": "\n\u00e0hi qu\u00e0nto a dir qual \u00e8ra \u00e8 c\u00f2sa d\u00f9ra\nviene a veder la g\u00e8nte ch\u00e9 min\u00ecstra\nper la qual tu su per lo v\u00ecre andava.\n\ncos\u00ec gi\u00f9 \u00e8, somme, ch\u00e9 per li empi c\u00f9i\nmi volvi, cominciai, com'a te de le pia,\nn\u00f3n , rimane al p\u00e0dre mio, figliuoli \u00e8.\n\ne 'l bu\u00f2n maestro m\u00eco mi dibattea\ndi compagn\u00eca ad ogne mover d'anca,\nper ch'io al d\u00f9ca mio, fa ch\u00e9 tu dolente.\n\nall\u00f3r mi volsi 'l v\u00ecse qu\u00e9l preso:\ne da qu\u00e9l ch'io mori' qui n\u00f3n mi sovvenni\nch\u00e9 tu testivi, spiriti \u00e8 molto, e\n\nvedi c\u00f3me l'ha dritte v\u00e8rso 'l cielo;\ned elli a me: qui s\u00f2n li eresiarche\nc\u00f3n lor seguaci, d'ogne setta, e m\u00f3lto\n\na l'altro polo, al t\u00e8mpo mi percosse\ne di molt'altri; e qui chi n\u00f3n vaneggia\nc\u00f3i dossi de le pi\u00e8 ferze rattero!.\n\np\u00f2scia li \u00f2cchi a la v\u00eca di le ciglia\ne un serp\u00e8nte ch\u00e9 per s\u00e8i 'l s\u00ec verso,\nch\u00e9 'l v\u00ecso m\u00eco tra quella g\u00e8nte \u00e8 \n\nn\u00f3n ci f\u00e0re \u00ecre a t\u00eczio ne' agiuna.\nlo d\u00f3lce p\u00e0dre mio, ma n\u00f3n \u00e8 molt'anni\na dirne gu\u00e8rra pr\u00e8sso a la sal\u00ecta\n\nda tutte parti per la gr\u00e0n foregita;\nma per la c\u00f2sta ch\u00e9 tra d\u00eca soletta,\ntal ch\u00e9 parturir li \u00f2cchi suoi dispregi.\n\nqu\u00e9sti \u00e8: la chi\u00e8sa ch\u00e9 tu n\u00f3n conce\nmolta virt\u00f9 v'\u00e8 n\u00f2va s\u00f2ma fanci\u00f9lla\npiangendo 'aspregiando, in ch\u00e9 ne face.\n\nma perche' s.u.a. nat\u00f9ra voma,\nper n\u00f3n intender cangiar, ma s\u00ec digi\u00f9no\nper conf\u00ecno al f\u00ecglio de la s.u.a. sp\u00e8ra\n\nl'altezza, ch\u00e9 ?, posa, se fat\u00e0glia\nsarebbe d\u00f9nque di d\u00eco cos\u00ec riarla,\nt\u00f2sto ch\u00e9 'l v\u00f2stro ciel fu s\u00ec congiunta.\n\nn\u00f3n mi rimira far mentr'io l'al mal princ\u00ecpio\ndi qu\u00e9sta d\u00e8stra d\u00e9l ciel mi convenne;\ne 'l t\u00f9o parlar m'invender vien c\u00f2l t\u00f9o\n\nqu\u00e9l mormorar de la g\u00e8nte ch\u00e9 s'amira.\n\n\nor ti rimani omai; che' 'l t\u00e8mpo \u00e8\nin qu\u00e9sti ne g\u00f3la di saper qual fu s\u00e0ngue\ndi s.u.a. vista, e a tal c\u00f3rte il \n\nfigliuol mio, ancor se tu n\u00f3n ti ficchi\nli disir\u00e0 venerai qu\u00e9sti giganti,\nch\u00e9 pr\u00eca per l'una r\u00f2ta \u00e8 in pianta.\n\ne c\u00f3me 'l maestro m\u00eco mi disse:\nqu\u00e9sti \u00e8 nembr\u00f2tto per lo c\u00f9i mal c\u00f3to\nle c\u00f9i \u00e9lla stoc\u00f3i piedi e ti scuopisi.\n\nall\u00f3r si mosse: qu\u00e9l di in gi\u00f9 a corni\nch\u00e9 tu sappi chi se' ch\u00e9 'l c\u00f3lmo n\u00f9lla\nch\u00e9 'l vis\u00ecbile \u00f3ltre st\u00e0nno \u00e8 lorda.\n\nn\u00f3n altrim\u00e9nti tu din\u00e0nzi li piedi,\ndisse 'l maestro; ma s\u00f2n quelle dee:\ndolor n\u00f3n vogliate, e per\u00f2 ch'altra scoda\n\nvidi d\u00f9e ch\u00e9 la m\u00f2rte si toglie.\nli \u00f2cchi molti a la m\u00e9nte vergogna leva,\ne la m\u00eca fante, e fece le corte\n\nch\u00e9 la g\u00e8nte ch\u00e9 piangendo n\u00f3n risponda\nle piante ninfe, c\u00f3n qu\u00e0nto s'aperse\nc\u00f3n le s\u00f9e parole stati dolente! via.\n\no d\u00f3lce stella, ch\u00e9 'ntorno pr\u00eca f\u00f2co\nmi pinse ghiotti andar, ne' s\u00ec ne tolse,\ne qu\u00e9l di r\u00e8tro a me ch\u00e9 n\u00f3n s\u00ec smarri.\n\nl'acqua ch\u00e9 vedea pi\u00f9 l\u00e0 gi\u00f9 di fora\ndal qu\u00e0le e il qu\u00e0nto de la v\u00ecva st\u00e9lla\nch\u00e9 de la fi\u00e0mma ch'\u00e8 va pi\u00f9 si sposta,\n\ntal di quella col\u00f9i ch\u00e9 pi\u00f9 si dice\nda la s\u00f9o sponda; cos\u00ec \u00e8 si tacque\nla qual tu su per lo m\u00e0re andava.\n\nqual \u00e8 col\u00f9i ch\u00e9 sol\u00e0ta in su la sc\u00e0la\nsi richiude, e 'l veder, di s\u00f3tto\nio n\u00f3n avrei vol\u00f9to ir per altra strada.\n\nma per trattar b\u00e8n sostener la gu\u00e8rra\n'n t\u00f9tto ch\u00e9 la sp\u00e8ra m\u00eca soletta;\nma la c\u00f2sta n\u00f3n perde \u00e0lto n\u00f2stro giro\n\ndi quella v\u00ecta son\u00f2 la sp\u00e8ra sogna:\nne la m\u00eca m\u00e9nte pi\u00f9 \u00e8 s\u00f9 n\u00f3n sosp\u00e8tto\nde la miglior voler ch\u00e9 n\u00f3n intenza.\n\no l'ombra d\u00e9l t\u00f9o sar\u00e0 cos\u00ec corta,\ndimmi, se s'io n\u00f3n ti fossi per altriste.\n\u00e0nzi m'assisisi ne la pr\u00ecma gente?\n\nche' qu\u00e9l poeta ch\u00e9 tu credi molte\nle vostre da la freddurita molte,\nvelando le chiavi in se' n\u00f3n \u00e8 pura?\".\n\nin su le man compiagni di\u00e8tro al s\u00e0no\nch\u00e9 mi compar\u00e8a queste dir, parole:\nvien di qu\u00e9llo ch\u00e9 n\u00f3n ch'altri s\u00eca spiace.\n\ne 'l tronco: qual s\u00f3vra s.u.a.\nnat\u00f9ra s\u00ec 'l vestito, ch\u00e9 'ntesi n\u00f9l\nper n\u00f3n aver pr\u00ecma ch'a l\u00f9i si diparte.\n\nlo d\u00f9ca m\u00eco \u00e0nima f\u00e0tto leva,\ns\u00ec ch\u00e9 la v\u00eca \u00e8 l\u00f9nga e n\u00f3n vea l'oro\ne ch\u00e9 la n\u00f2va c\u00f2sta n\u00f3n coscende\".\n\nse d\u00e9l n\u00f3n f\u00f2sse la c\u00f2sta di malebol,\naccesi su per la s.u.a. v\u00ecta\ngi\u00e0 t\u00e0nto pu\u00f2 pensar, ch'i' n\u00f3n fui n\u00f2to\n\na p\u00e9na fuoro e di l\u00e0 dal di qu\u00e0nto\npi\u00f9 a li \u00f2cchi suoi sospiri domandai\nper veder cos\u00ec fosse, n\u00f3n me dichina.\n",
        "temp_1.5": "\na quella f\u00f3ce ha elli or dr\u00ectta l'alata,\nper\u00f2 ch\u00e9 s\u00e8mpre qu\u00ecvi si ricoglie alma,\ns\u00ec ch\u00e9 'l t\u00e8mpo m\u00eco s\u00f3le altra rifiede.\n\nd\u00e9l m\u00f2do andava d\u00e9l p\u00f3nte su la valle,\nch\u00e9 mi compar\u00e8a venni, pianger parlare,\ne 'l mar \u00e8 la ver\u00e0to ch\u00e9 'l parla:\n\nn\u00f3n so, ma n\u00f3n so, ma, che' per \na trarrotti d'erro un p\u00f2co mi favella:\nb\u00e8n li piedi e tender qual tu se' vedi?.\n\ned elli a me: nessun m'\u00e8 f\u00e0tto \u00e0ncora\ngi\u00f9 per la vera tr\u00ecsta di l\u00f9i chiostra:\ndov'io stavai c\u00f3me tu vuo' ch\u00e9 'l nermi\n\nper che, perch'io l\u00f2co \u00f3ltre parl\u00f2 s\u00e0nza\nla f\u00e0ccia de li \u00f2cchi suoi dov'io fossi\na c\u00f9i n\u00f9lla spondi a me c'ha n\u00f3me soggiorno.\n\nn\u00f3n altrim\u00e9nti tu la montati argosciati\na li altri, disse a se': ti d\u00ec in c\u00f3nca\nqu\u00e9sta fi\u00e0mma staria che' men malebranche.\n\ne qu\u00e0ndo fui piangendo s\u00e0nza lacerca,\nch\u00e9 li avea fatti a l'alber veder la f\u00e0ccia\nper la ver\u00e0ce tenciola fu\u00f2r d\u00e9l richiede.\n\no frate, ch\u00e9 n\u00f3n per fom\u00f2 i morti\na l'altro lavolont\u00e0, di ch\u00e9 chiede l'erba\nm'ha demonio, \u00f3ra pr\u00eca ch\u00e9 qu\u00e0ttro strale\n\nle leggi son, ch\u00e9 'l dolor levati\nch\u00ecna gi\u00e0 l'ombra qu\u00e0si al l\u00e8tto piano,\nqu\u00e0ndo chinava, a la divina grotta.\n\no ch\u00e9 ne la v\u00ecsta mia, qu\u00ecnta s\u00f2la\nd'una rimanenta e 'l cor qu\u00e0ndo a posta:\nfatt'ha lev\u00e0to per s.u.a. cornice.\n\nqu\u00ecnci rivede \u00e0ncora a la nostra f\u00ecda\ngi\u00f9 per l'antica s.u.a. innatate;\ne per pi\u00f9 salir pot\u00e0nto s\u00f2l di forsa,\n\ncos\u00ec s\u00e9n va, se n\u00f3n f\u00f2sse turbato;\nma c\u00f3me col\u00f9i ch\u00e9 l'ha alli appagato,\nqu\u00e9i ch\u00e9 'nparlava, offeta n\u00f9lla fiede.\n\ndi qua, par\u00e8tal ne l'omero bianco;\nma ch\u00e9 mi largiscon qui la lor parvente,\nper ch\u00e9 d\u00e9l veder vi mosse \u00f3mbra resta.\n\na quelle cerchi di col\u00f3ro a le 'nsegne\ns\u00e9n giva; e n\u00f3n ferr\u00f2 che' mi m\u00e9tte\nda l'altro polore, e vidi qu\u00e0ttro panta\n\na p\u00e9na pensier, contenta la forti.\nt\u00e0nto pi\u00f9 piena, ch\u00e9 la 've la p\u00f2rta\ndi molti, e ; cos\u00ec s\u00f2n ne livi.\n\ncos\u00ec 'l teggia d\u00e9l caron s\u00ec de p\u00f2rta\nparole, l\u00e0 d\u00f3ve 'nduna n\u00f2tte st\u00e0nno\nu' b\u00e8n si discerno i piedi e de le mani;\n\ne 'l d\u00f9ca m\u00eco ch\u00e9 si mova p\u00e0rte\ndi color malebolge d\u00f9e 'l ghirlande,\ntra li scheggion de le qu\u00e0tto qu\u00e0tto quatgue,\n\nsicuram\u00e9nte om\u00e0i a me ti riedi,\nper ch'io divenni dal visid\u00e8 per le chiome\nd\u00e9l s\u00f9o voler dis\u00eco fa s\u00ec crudele.\n\nch\u00e9 dal qu\u00ecnto n\u00f3n si p\u00f2co n\u00f3n si p\u00e0rte\na t\u00e0nto s\u00e9gno e pi\u00f9 trova molt'altro,\nch\u00e9 pi\u00f9 a l'una p\u00e0rte e d'altra \u00e8 fatte;\n\ne la man d\u00e8stra p\u00e0rte oriental saleta.\n\n\n\nvenimmo p\u00f2i in sul l\u00ecto diserto,\nch\u00e9 gi\u00e0 m\u00e0i n\u00f3n si par\u00e8a dr\u00ectta e queta,\nne' 'l qual r, ne' grande, ne' a lei\n\ndi quella piet\u00e0 ch\u00e9 gi\u00e0 s'imbiancava mota\nsi move ciascuna per s.u.a. costa\nla qual molta in albia, e albia in mar fedino.\n\nl'altro ch\u00e9 ne la v\u00ecsta \u00e8 f\u00e0tta invota,\ncos\u00ec si consona: in v\u00eca l\u00f9i sape,\ns\u00ec ch\u00e9 la v\u00eca c\u00f2l ciel n\u00f3n si paia.\n\ncos\u00ec disse il fiammeggiar d\u00e9l c\u00e9rchio tr\u00ecsto\ndi quella cr\u00f3ce f\u00eca tra 'l princ\u00ecpio e negra\na una, a due, a tre, e l'altre st\u00e0nno\n\ntimidette atterrando l'occhio e 'l gr\u00e0n muso;\ne la v\u00f3ce m\u00eca disse: in p\u00e0rte g\u00ec\nqu\u00e9sta \u00e8 la chiama, e per\u00f2 s\u00f2la sc\u00f2la\n\ndal c\u00f2rpo ond'ella stessa s'\u00e8 r\u00e8tro al m\u00f3nte ci\u00e8lo\nrispuose: qu\u00e0nto f\u00eca l\u00f9nga \u00e8 da me;\nma n\u00f3n s\u00ec ch\u00e9 pa\u00f9ra n\u00f3n \u00e8 gi\u00f9nto.\n\nsu la sponda d'un m\u00f2do de la sp\u00e8ra \nch\u00e9 s\u00e8mpre 'l gelan, ch\u00e9 n\u00f3n si rammen\nal v\u00f3lo mio, per n\u00f3n aver la 'ntesa\n\ndi ch\u00e9 ciascun di c\u00f2sa mi s'inforca;\nper ch\u00e9 la tua fort\u00f9na \u00e8 color decreta\npi\u00f9 ch\u00e9 nostra per etterno la vita.\n\nqueste parole, p\u00f2i ch\u00e9 mostr\u00f2 vota,\ntorna tutta da s.u.a. informata,\nper \u00ecndi la c\u00f2sta e ch'\u00e8 pi\u00f9 di vita;\n\ne sem romagra, per ch\u00e9 s'acquist\u00f2 piace\na l'alto lavostra m\u00eca \u00e8 s\u00ec devota,\nch\u00e9 la s.u.a. vision tien disare;\n\ne venne g\u00e8nte qui per qu\u00e9sto stolere,\nn\u00f3n s\u00ec che, se l\u00f2co m'\u00e8 t\u00f2lto sole;\nio n\u00f3n veder\u00f2 c\u00f3me ch\u00e9 piange e dice.\n\nn\u00f3i leggiavamo un gi\u00f3rno per dil\u00e8tto scrivo;\ns\u00ec che, se lo 'ngi\u00f9so la pi\u00f9 ti mi\nla verit\u00e0 d\u00e9lle genti s\u00ec trista.\n\ne c\u00f3me 'l s\u00f9o miseric\u00f2rre alqu\u00e0nto venta\nde la m\u00eca virt\u00f9 s'ella v\u00ecta vera,\nch\u00e9 n\u00f3n ha \u00f2cchio di l\u00e0 gi\u00f9 pianger spia.\n\nesce di m\u00e0no a l\u00f9i ch\u00e9 la vagheggia\npr\u00ecma ch\u00e9 sia, a gu\u00ecsa d\u00e9l fin suma,\nperche' 'l m\u00f3ndo la ved\u00f9ta \u00e8 diparte.\n"
    }
}